django_tg_bot_framework/__init__.py
django_tg_bot_framework/apps.py
django_tg_bot_framework/contextvars_tools.py
django_tg_bot_framework/debug_states.py
django_tg_bot_framework/decorators.py
django_tg_bot_framework/exceptions.py
django_tg_bot_framework/models.py
django_tg_bot_framework/routes.py
django_tg_bot_framework/state_machine.py
django_tg_bot_framework/states.py
django_tg_bot_framework/views.py
django_tg_bot_framework-1.0.0.dist-info/METADATA
django_tg_bot_framework-1.0.0.dist-info/WHEEL
django_tg_bot_framework-1.0.0.dist-info/RECORD
