Metadata-Version: 2.1
Name: django-tg-bot-framework
Version: 1.0.0
Summary: Framework for building telegram bots
License: GNU GPLv3
Author: Ilya Osipov
Author-email: 070809010@mail.ru
Requires-Python: >=3.11,<4.0
Classifier: License :: Other/Proprietary License
Classifier: Programming Language :: Python :: 3
Classifier: Programming Language :: Python :: 3.11
Requires-Dist: django (>=4,<5)
Requires-Dist: django-storages (>=1.13.2,<2.0.0)
Requires-Dist: pytest-django (==4.5.2)
Requires-Dist: tg_api (==1.0.0)
